ai_mysql_translator/__init__.py
ai_mysql_translator/main.py
ai_mysql_translator/prompts.py
ai_mysql_translator-2025.12.21101721.dist-info/METADATA
ai_mysql_translator-2025.12.21101721.dist-info/WHEEL
ai_mysql_translator-2025.12.21101721.dist-info/top_level.txt
ai_mysql_translator-2025.12.21101721.dist-info/RECORD
