Metadata-Version: 2.4
Name: ai-mysql-translator
Version: 2025.12.21101721
Summary: A new package enables AI systems to securely interact with MySQL databases by translating natural language queries into structured SQL commands. It processes user text input to generate safe, validate
Author-email: ai-mysql-translator <hi@eugene.plus>
License: MIT
Project-URL: Homepage, https://github.com/chigwell/ai-mysql-translator
Requires-Python: >=3.9
Requires-Dist: langchain-llm7>=0.0.0
Requires-Dist: llmatch-messages>=0.0.0
Requires-Dist: langchain-core>=0.3.0
